auto_llm_chatbot/__init__.py
auto_llm_chatbot/chatbot.py
auto_llm_chatbot/chroma_handler.py
auto_llm_chatbot/llm.py
auto_llm_chatbot/models.py
auto_llm_chatbot-0.1.4.dist-info/LICENSE.txt
auto_llm_chatbot-0.1.4.dist-info/METADATA
auto_llm_chatbot-0.1.4.dist-info/WHEEL
auto_llm_chatbot-0.1.4.dist-info/top_level.txt
auto_llm_chatbot-0.1.4.dist-info/RECORD
