Metadata-Version: 2.1
Name: auto_llm_chatbot
Version: 0.1.4
Summary: Auto LLM Chatbot is a Python package that simplifies chatbot development by automatically managing chat history using local vector databases like Chroma DB.
Home-page: https://github.com/dipeshpaulsystango/auto_llm_chatbot
Author: Dipesh Paul
Author-email: dipesh.paul@systango.com
Classifier: Programming Language :: Python :: 3
Classifier: License :: OSI Approved :: MIT License
Classifier: Operating System :: OS Independent
Requires-Python: >=3.9
License-File: LICENSE.txt
Requires-Dist: ollama==0.3.2
Requires-Dist: openai==1.43.0
Requires-Dist: lazyme==0.0.27
Requires-Dist: chromadb==0.5.4
